[
  {"title":"서울 서대문구 북아현동 e편한세상신촌 84㎡ 21.34억 신고가","source":"이투데이","url":"https://www.etoday.co.kr/news/view/2509171","date":"2025-09-22","summary":"서대문구 북아현동 e편한세상신촌(1910세대) 21.34억 매매, 직전 대비 +2.04억(10%) 상승.","category":"price","comment":"북아현·가재울 정비와 2·5호선 도심 접근성으로 토허 속에서도 신축 실수요가 가격 지지."},
  {"title":"서울 서대문구 서대문푸르지오센트럴파크 75.49㎡ 16.95억","source":"국토부 실거래가","url":"https://apt2.me/","date":"2026-05-30","summary":"서대문구 서대문푸르지오센트럴파크 전용 75.49㎡ 16.95억 매매, 저점 대비 +3.15억 반등.","category":"price","comment":"도심 준신축이 저점 대비 크게 반등, 규제하 실수요가 우량 단지로 선별 집중."},
  {"title":"서울 중구 신당동 남산타운 84.88㎡ 17.1억","source":"국토부 실거래가","url":"https://zippoom.com/blog/jung-gu","date":"2026-03-10","summary":"중구 신당동 남산타운(5150세대) 전용 84.88㎡ 17.1억, 114.9㎡는 2월 21억 거래.","category":"price","comment":"6·3호선 더블역세권 대단지 구축이 도심 가격 지지, 신당 정비 기대가 상방."},
  {"title":"서울 중구 황학동 롯데캐슬 59.94㎡ 9.97억","source":"국토부 실거래가","url":"https://www.aptbong.com/junggu","date":"2026-03-13","summary":"중구 황학동 롯데캐슬(2008년) 전용 59.94㎡ 9.97억 매매.","category":"price","comment":"도심 전용 59㎡ 준신축이 10억 문턱, 6억 상한·토허 실거주 아래 소형 실수요 가격대."},
  {"title":"서울 중구 황학동 청계노르웨이숲 404세대 2028년 입주 예정","source":"호갱노노","url":"https://hogangnono.com/apt/2O75","date":"2025-10-06","summary":"중구 황학동 청계노르웨이숲(404세대) 2028년 7월 입주 예정, 신당·황학 신규 공급.","category":"price","comment":"도심 입주 희소 속 신규 공급 단지로 준공 시점 인근 수급 완충."},
  {"title":"서울 관악구 힐스테이트관악센트씨엘 84.95㎡ 16억 신고가","source":"국토부 실거래가","url":"https://apt2.me/apt/AptDaily.jsp?area=11620","date":"2026-05-28","summary":"관악구 힐스테이트관악센트씨엘 전용 84.95㎡ 16억, 직전 대비 +2.25억 신고가.","category":"price","comment":"봉천 신축 국평이 16억 신고가, 토허에도 신축·역세권에 실수요 집중."},
  {"title":"서울 마포구 마포에피트어바닉 46.24㎡ 11.85억 신고가","source":"국토부 실거래가","url":"https://apt2.me/","date":"2026-06-13","summary":"마포구 마포에피트어바닉 전용 46.24㎡ 11.85억 신고가.","category":"price","comment":"도심 마포 신축은 소형도 신고가, 1~2인 실수요가 소형 신축에 집중."},
  {"title":"서울 동대문구 전농동 래미안크레시티 84㎡ 16억","source":"이투데이","url":"https://www.etoday.co.kr/news/view/2509171","date":"2025-09-22","summary":"동대문구 전농동 래미안크레시티 16억(+0.4억), 청계한신휴플러스 12.9~13.25억 거래.","category":"price","comment":"청량리 환승·개발 기대가 동대문 대단지 가격 지지."},
  {"title":"서울 양천구 신정동 래미안목동아델리체 84.58㎡ 10억 신고가","source":"국토부 실거래가","url":"https://apt2.me/","date":"2026-06-04","summary":"양천구 신정동 래미안목동아델리체 전용 84.58㎡ 10억 신고가(+0.3억).","category":"price","comment":"목동 재건축 기대가 인근 신축까지 확산, 학군·정비가 양천 가격 단계적 지지."},
  {"title":"서울 용산구 이촌동 래미안첼리투스 124.01㎡ 54억","source":"국토부 실거래가","url":"https://zippoom.com/yongsan-chelitus","date":"2025-07-22","summary":"용산구 이촌동 래미안첼리투스(2015년) 전용 124.01㎡ 54억 매매.","category":"price","comment":"용산공원·한강변 대형 신축 50억대, 국제업무지구 기대가 이촌 가격 지지."},
  {"title":"서울 용산구 이촌동 LG한강자이 63억 매매","source":"국토부 실거래가","url":"https://zippoom.com/yongsan-ichon","date":"2026-01-30","summary":"용산구 이촌동 LG한강자이 63억 매매, 이촌동 최고가 거래.","category":"price","comment":"한강뷰 대형은 토허에도 별도 수급으로 초고가 강세 유지."},
  {"title":"서울 용산구 이촌동 래미안첼리투스 124.01㎡ 전세 20억","source":"국토부 실거래가","url":"https://zippoom.com/yongsan-chelitus","date":"2025-12-29","summary":"용산구 이촌동 래미안첼리투스 전용 124.01㎡ 전세 20억 신고(임대차).","category":"price","comment":"입주물량 부족·고가 전세 수요가 용산 임대차 가격 견인."},
  {"title":"서울 성동구 하왕십리동 센트라스 59.59㎡ 18.8억","source":"국토부 실거래가","url":"https://www.aptbong.com/seongdong","date":"2026-05-11","summary":"성동구 하왕십리동 센트라스(2016년) 전용 59.59㎡ 18.8억 매매.","category":"price","comment":"왕십리뉴타운 신축 전용 59㎡가 19억 근접, 도심 직주근접 수요로 강북 대장 견조."},
  {"title":"서울 성동구 하왕십리동 왕십리자이 59.99㎡ 17.15억","source":"국토부 실거래가","url":"https://www.aptbong.com/seongdong","date":"2026-05-09","summary":"성동구 하왕십리동 왕십리자이(2017년) 전용 59.99㎡ 17.15억 매매.","category":"price","comment":"왕십리 신축 소형 17억대 유지, 규제하 실거주 선호 단지 방어력."},
  {"title":"서울 성동구 행당동 대림e편한세상 59.96㎡ 16.65억","source":"국토부 실거래가","url":"https://www.aptbong.com/seongdong","date":"2026-05-09","summary":"성동구 행당동 대림e편한세상(2000년) 전용 59.96㎡ 16.65억 매매.","category":"price","comment":"준구축 전용 59㎡도 16억대, 신축 상승이 인근 구축으로 전이."},
  {"title":"서울 성동구 성수동2가 현대I-PARK 104.56㎡ 21.9억","source":"국토부 실거래가","url":"https://www.aptbong.com/seongdong","date":"2026-05-09","summary":"성동구 성수동2가 현대I-PARK(2003년) 전용 104.56㎡ 21.9억 매매.","category":"price","comment":"성수 대형 22억 선, 성수전략정비·지식산업 클러스터 기대가 중대형 지지."},
  {"title":"서울 성동구 금호동4가 힐스테이트서울숲리버 59.98㎡ 14.55억","source":"국토부 실거래가","url":"https://zippoom.com/seongdong-geumho","date":"2025-12-30","summary":"성동구 금호동4가 힐스테이트서울숲리버 전용 59.98㎡ 14.55억 매매.","category":"price","comment":"금호·옥수 한강변 신축 소형 14억대, 강남 접근성 프리미엄 반영."},
  {"title":"서울 광진구 자양동 더샵스타시티 122.88㎡ 26.25억","source":"KB부동산","url":"https://kbland.kr/se/c/14694","date":"2026-06-19","summary":"광진구 자양동 더샵스타시티(2007년) 전용 122.88㎡ 26.25억, 5월 24.25억 거래.","category":"price","comment":"건대입구 더블역세권 대형 24~26억대, 광진 공급 희소로 대단지 우상향."},
  {"title":"서울 광진구 광장동 광장힐스테이트 130.16㎡ 29.85억","source":"국토부 실거래가","url":"https://zippoom.com/gwangjin-gwangjang","date":"2025-10-19","summary":"광진구 광장동 광장힐스테이트(2012년) 전용 130.16㎡ 29.85억 매매.","category":"price","comment":"광장동 학군·한강변 대형 30억 근접, 우량 학군지 수요가 가격 지지."},
  {"title":"서울 광진구 광장동 광장힐스테이트 59.99㎡ 전세 5.75억","source":"국토부 실거래가","url":"https://zippoom.com/gwangjin-gwangjang","date":"2025-12-09","summary":"광진구 광장동 광장힐스테이트 전용 59.99㎡ 전세 5.75억 신고(임대차).","category":"price","comment":"학군지 전용 59㎡ 전세 5억대 후반, 입주 감소·토허 임대 위축이 전세 견인."},
  {"title":"서울 동작구 흑석동 아크로리버하임 84.9㎡ 34.6억","source":"국토부 실거래가","url":"https://zippoom.com/dongjak-heukseok","date":"2025-10-14","summary":"동작구 흑석동 아크로리버하임 전용 84.9㎡ 34.6억, 59.91㎡는 1월 26.6억.","category":"price","comment":"흑석뉴타운 9호선·한강 입지로 84㎡ 35억 근접, 강남 접근성이 가격 견인."},
  {"title":"서울 동작구 흑석동 한강현대 83.47㎡ 24.5억","source":"국토부 실거래가","url":"https://zippoom.com/dongjak-heukseok","date":"2026-01-31","summary":"동작구 흑석동 한강현대 전용 83.47㎡ 24.5억 매매.","category":"price","comment":"재건축·리모델링 기대 구축도 24억대, 정비 모멘텀이 노후 단지 지지."},
  {"title":"서울 동작구 흑석동 흑석한강센트레빌 59.95㎡ 20.4억","source":"국토부 실거래가","url":"https://zippoom.com/dongjak-heukseok","date":"2026-02-20","summary":"동작구 흑석동 흑석한강센트레빌 전용 59.95㎡ 20.4억 매매.","category":"price","comment":"흑석 신축 전용 59㎡가 20억 돌파, 한강·9호선 입지가 소형까지 고가."},
  {"title":"서울 동작구 흑석동 흑석뉴타운롯데캐슬에듀포레 59.87㎡ 21.3억","source":"국토부 실거래가","url":"https://zippoom.com/dongjak-heukseok","date":"2026-01-31","summary":"동작구 흑석동 흑석뉴타운롯데캐슬에듀포레 전용 59.87㎡ 21.3억, 85㎡ 25억.","category":"price","comment":"정비 완료지 신축이 동작 가격 견인, 상도 동작센트럴자이 등 공급 대기."},
  {"title":"서울 서초구 반포동 아크로리버파크 84㎡ 63억 신고가","source":"조선비즈","url":"https://news.nate.com/view/20260531n07133","date":"2026-05-19","summary":"서초구 반포동 아크로리버파크 전용 84㎡ 63억 신고가(직전 평균 약 58억).","category":"price","comment":"반포 대장 84㎡ 60억대 신고가, 강남 재건축 기대·비규제 급등이 신축 전이."},
  {"title":"서울 서초구 반포동 반포자이 84.99㎡ 48.8억","source":"국토부 실거래가","url":"https://zippoom.com/seocho-banpo","date":"2025-09-20","summary":"서초구 반포동 반포자이(2009년) 전용 84.99㎡ 48.8억 매매.","category":"price","comment":"반포 대단지 국평 50억 근접, 재건축 인접 구축 강세가 반포 전반 견인."},
  {"title":"서울 서초구 반포동 반포써밋 84.97㎡ 37.8억","source":"국토부 실거래가","url":"https://zippoom.com/seocho-banpo","date":"2025-09-16","summary":"서초구 반포동 반포써밋 전용 84.97㎡ 37.8억 매매.","category":"price","comment":"반포권 신축 국평 38억 선, 학군·교통·한강 인접이 서초 신축 프리미엄."},
  {"title":"서울 서초구 반포동 디에이치반포라클라스 59.99㎡ 36.5억","source":"국토부 실거래가","url":"https://zippoom.com/seocho-banpo","date":"2025-09-27","summary":"서초구 반포동 디에이치반포라클라스 전용 59.99㎡ 36.5억 매매.","category":"price","comment":"반포 신축은 전용 59㎡도 36억대, 소형까지 평당 2억 근접 초고가."},
  {"title":"서울 성북구 길음동 래미안길음센터피스 84.99㎡ 17.8억","source":"국토부 실거래가","url":"https://zippoom.com/seongbuk-gileum","date":"2026-04-18","summary":"성북구 길음동 래미안길음센터피스 전용 84.99㎡ 17.8억 매매.","category":"price","comment":"길음뉴타운 대장 국평 18억 선, 정비 완료 대단지가 강북 실수요 상단 형성."},
  {"title":"서울 성북구 길음동 길음뉴타운래미안6단지 84㎡ 15.25억","source":"국토부 실거래가","url":"https://zippoom.com/seongbuk-gileum","date":"2026-04-04","summary":"성북구 길음동 래미안6단지 전용 84㎡ 15.25억, 59.37㎡ 13.05억 매매.","category":"price","comment":"길음 정비단지 84·59㎡가 13~15억대, 4호선·우이신설 접근성으로 견조."},
  {"title":"서울 성북구 길음동 길음뉴타운래미안8단지 84.82㎡ 12.9억","source":"국토부 실거래가","url":"https://zippoom.com/seongbuk-gileum","date":"2026-04-22","summary":"성북구 길음동 래미안8단지 전용 84.82㎡ 12.9억 매매.","category":"price","comment":"길음 1세대 정비단지 13억 선, 신축 대비 가격 메리트로 실거주 거래 유지."},
  {"title":"서울 성북구 보문동 보문리슈빌하우트 59.79㎡ 11.5억","source":"국토부 실거래가","url":"https://zippoom.com/seongbuk","date":"2025-10-02","summary":"성북구 보문동1가 보문리슈빌하우트 전용 59.79㎡ 11.5억 매매.","category":"price","comment":"보문·삼선 정비 신축 전용 59㎡ 11억대, 도심 접근성이 성북 동남부 지지."},
  {"title":"서울 구로구 고척동 벽산 84.88㎡ 10.7억","source":"국토부 실거래가","url":"https://www.aptbong.com/guro","date":"2026-05-25","summary":"구로구 고척동 벽산(2003년) 전용 84.88㎡ 10.7억 매매.","category":"price","comment":"고척 준신축 국평 10억대, 고척돔·서부간선 지하화가 구로 서부 지지."},
  {"title":"서울 구로구 개봉동 한마을 59.57㎡ 9.3억","source":"국토부 실거래가","url":"https://www.aptbong.com/guro","date":"2026-05-25","summary":"구로구 개봉동 한마을(1999년) 전용 59.57㎡ 9.3억 매매.","category":"price","comment":"개봉 구축 전용 59㎡ 9억대, 1호선·정비 기대가 중소형 실수요 지지."},
  {"title":"서울 구로구 고척동 대우 84.98㎡ 7.5억","source":"국토부 실거래가","url":"https://www.aptbong.com/guro","date":"2026-05-25","summary":"구로구 고척동 대우(1999년) 전용 84.98㎡ 7.5억, 59.96㎡ 6.8억 매매.","category":"price","comment":"구축 국평 7억대로 신축과 격차, 연식·정비 단계가 가격 차별화."},
  {"title":"서울 구로구 신도림동 신도림4차e편한세상 84.78㎡ 16.95억","source":"국토부 실거래가","url":"https://zippoom.com/guro-sindorim","date":"2025-10-13","summary":"구로구 신도림동 신도림4차e편한세상 전용 84.78㎡ 16.95억, 117.7㎡ 19억.","category":"price","comment":"신도림 대장 국평 17억 선, 1·2호선 환승·디큐브 상권이 구로 최상단."},
  {"title":"서울 구로구 아파트 최고가 대비 2~29% 하락(구축 약세)","source":"서울경제뉴스","url":"https://www.seouleconews.com/news/articleView.html?idxno=100386","date":"2026-01-26","summary":"구로구 실거래가 직전 최고 대비 2~29% 하락, 고척파크푸르지오 9.25억(-10%), LG신도림자이 10.5억(-7%).","category":"macro","comment":"토허·대출규제로 외곽 구축이 먼저 조정, 신축 방어·구축 하락의 차별화 장세."},
  {"title":"서울 금천구 독산동 금천롯데캐슬골드파크1차 84.81㎡ 12.4억","source":"뉴스와","url":"https://www.news-wa.com/article/2026/02/05/20260205500008","date":"2026-01-31","summary":"금천구 독산동 금천롯데캐슬골드파크1차 전용 84.81㎡ 12.4억(금천구 주간 최고가).","category":"price","comment":"금천구청역 역세권 신축 국평 12억대, 정비·역세권 개발 기대가 대장 견인."},
  {"title":"서울 금천구 독산동 84.97㎡ 11.5억·59.96㎡ 10.1억","source":"국토부 실거래가","url":"https://zippoom.com/geumcheon","date":"2026-06-03","summary":"금천구 독산동 전용 84.97㎡ 11.5억(6/3), 전용 59.96㎡ 10.1억(5/27) 매매.","category":"price","comment":"독산 신축 전용 59㎡도 10억 진입, 신안산선·역세권 개발이 중소형 견인."},
  {"title":"서울 금천구 독산동 금천현대 84.83㎡ 6.73억","source":"뉴스와","url":"https://www.news-wa.com/article/2026/02/05/20260205500008","date":"2026-01-31","summary":"금천구 독산동 금천현대 전용 84.83㎡ 6.73억, 가산동 두산 59.84㎡ 6억.","category":"price","comment":"구축 국평 6억대로 신축과 2배 격차, 정비 진척도가 단지별 가격 가름."},
  {"title":"서울 중랑구 면목동 사가정센트럴아이파크 84.87㎡ 11.95억","source":"국토부 실거래가","url":"https://zippoom.com/jungnang","date":"2025-10-19","summary":"중랑구 면목동 사가정센트럴아이파크 전용 84.87㎡ 11.95억, 114.9㎡ 16억.","category":"price","comment":"면목 신축 국평 12억 선, 7호선 사가정역세권·재정비 기대가 대장 형성."},
  {"title":"서울 중랑구 묵동 e편한세상화랑대 84.9㎡ 12.2억","source":"국토부 실거래가","url":"https://zippoom.com/jungnang-mukdong","date":"2026-02-21","summary":"중랑구 묵동 e편한세상화랑대 전용 84.9㎡ 12.2억(2025.10 10.9억 대비 상승).","category":"price","comment":"묵동 신축 국평 12억대 상승, 6호선·경춘선 접근성과 학군 수요가 지지."},
  {"title":"서울 중랑구 면목동 한양수자인사가정파크 84.98㎡ 10.5억","source":"국토부 실거래가","url":"https://zippoom.com/jungnang","date":"2025-10-16","summary":"중랑구 면목동 한양수자인사가정파크 전용 84.98㎡ 10.5억 매매.","category":"price","comment":"면목 신축 국평 10억대 중반, 면목선·상봉터미널 개발이 중랑 중심부 지지."},
  {"title":"서울 중랑구 망우동 신내역금강펜테리움센트럴파크 84.99㎡ 8.42억","source":"국토부 실거래가","url":"https://www.aptbong.com/jungnang","date":"2025-11-13","summary":"중랑구 망우동 신내역금강펜테리움센트럴파크(2021년) 전용 84.99㎡ 8.42억.","category":"price","comment":"신내·망우 신축 국평 8억대, 6·경춘선 신내역세권이 중랑 동북부 하단 지지."},
  {"title":"경기 구리시 갈매동 한라비발디 84.58㎡ 7.4억·갈매더샵나인힐스 69.82㎡ 6.9억","source":"국토부 실거래가","url":"https://zippoom.com/guri-galmae","date":"2026-06-03","summary":"구리시 갈매동 한라비발디 전용 84.58㎡ 7.4억(6/3), 갈매더샵나인힐스 69.82㎡ 6.9억(6/2). 갈매 평당 3047만(+8.1%).","category":"price","comment":"비규제 택지 신축 7억 안팎, 서울 규제 풍선효과·8호선 호재가 갈매 지지."},
  {"title":"경기 구리시 8호선 별내선 개통·GTX-B 갈매역 검토","source":"부동산 보도","url":"https://news.nate.com/view/20240828n36080","date":"2024-08-28","summary":"8호선 별내선 2024.8 개통(구리역 등 3개역, 잠실 27분), GTX-B 갈매역 신설 거론.","category":"price","comment":"강남 접근성 개통이 외곽 택지 재평가, 호재 선반영으로 추가 상승폭은 제한."},
  {"title":"경기 평택시 고덕동 제일풍경채센텀3차 84㎡ 7.03억 신고가","source":"헤럴드경제","url":"https://biz.heraldcorp.com/article/10668303","date":"2026-02-03","summary":"평택 고덕 제일풍경채센텀3차 전용 84㎡ 7.03억 신고가(직전 7억), 대장 파라곤 85㎡ 최고 9.8억.","category":"price","comment":"삼성 평택캠퍼스 배후·미분양 감소로 고덕 반등, 반도체 투자 재개가 외곽 신도시 견인."},
  {"title":"경기 평택시 고덕국제신도시 수자인풍경채 84㎡ 5억 초중반 청약(6/11)","source":"헤럴드경제","url":"https://biz.heraldcorp.com/article/10729551","date":"2026-05-03","summary":"평택 고덕 3단계 수자인풍경채 1·2단지(1126가구) 6/11 청약, 분상제 84㎡ 5억 초중반, 1호선 급행 서정리역.","category":"price","comment":"분상제 저렴 신축 공급 본격화, 삼성 직주근접 수요가 분양시장 유입."},
  {"title":"경기 평택시 아파트값 119주 만에 상승 전환(+0.14%, 6월 2주)","source":"이투데이","url":"https://www.etoday.co.kr/news/view/2594469","date":"2026-06-17","summary":"부동산원 기준 평택 매매가 6월 2주 +0.14%, 2024.2 이후 119주 만에 상승 전환, 고덕·지제역 견인.","category":"macro","comment":"삼성 P4 재개로 배후 수요 회복, 반도체 업황이 지역 부동산 사이클 좌우."},
  {"title":"경기 과천시 중앙동 푸르지오써밋 84.99㎡ 25.7억·래미안에코팰리스 84.94㎡ 19.8억","source":"국토부 실거래가","url":"https://zippoom.com/gwacheon","date":"2026-05-08","summary":"과천 중앙동 푸르지오써밋 전용 84.99㎡ 25.7억(5/8), 래미안에코팰리스 84.94㎡ 19.8억(5/6).","category":"price","comment":"강남 인접·정비 프리미엄으로 과천 국평 25억대, 준서울급 입지가 규제에도 견조."},
  {"title":"경기 과천시 부림동 주공9단지 83.2㎡ 28.4억·과천위버필드 84.98㎡ 23.8억","source":"국토부 실거래가","url":"https://zippoom.com/gwacheon","date":"2026-01-30","summary":"과천 부림동 주공9단지 전용 83.2㎡ 28.4억(평당 약 1.13억), 과천위버필드 84.98㎡ 23.8억.","category":"price","comment":"재건축 구축 대지지분 프리미엄이 신축가 상회, 과천 정비 기대가 가격 견인."},
  {"title":"경기 과천시 부림동 과천센트럴파크푸르지오써밋 59.92㎡ 19.9억","source":"국토부 실거래가","url":"https://zippoom.com/gwacheon","date":"2026-05-23","summary":"과천 부림동 과천센트럴파크푸르지오써밋 전용 59.92㎡ 19.9억, 114.9㎡ 28억.","category":"price","comment":"과천은 전용 59㎡ 신축도 20억 근접, 공급 희소·강남 접근성이 소형까지 고가."},
  {"title":"경기 광명시 광명자이힐스테이트SKVIEW 71.84㎡ 13.13억 신고가","source":"국토부 실거래가","url":"https://apt2.me/","date":"2026-05-23","summary":"광명시 광명자이힐스테이트SKVIEW 전용 71.84㎡ 13.13억·71.36㎡ 12.6억 신고가.","category":"price","comment":"광명뉴타운 정비·신안산선 호재로 신축 13억대 신고가, 서울 인접 준규제권 강세."},
  {"title":"경기 성남시 분당구 느티마을4단지 58.71㎡ 17.5억·판교알파리움1단지 64억","source":"국토부 실거래가","url":"https://apt2.me/","date":"2026-05-27","summary":"분당 정자동 느티마을4단지 전용 58.71㎡ 17.5억(저점 대비 +6.1억), 판교알파리움1단지 64억 신고가.","category":"price","comment":"1기 신도시 재건축 선도지구 기대가 분당 구축 소형 대지지분 견인, 판교 대장 신고가."},
  {"title":"경기 성남시 분당구 정자동 정든마을우성6단지 84㎡ 9.2억","source":"이투데이","url":"https://www.etoday.co.kr/news/view/2509171","date":"2025-09-22","summary":"분당 정자동 정든마을우성6단지 9.2억(+0.95억, 11%) 상승 거래.","category":"price","comment":"1기 신도시 정비 기대가 분당 중소형 구축 수요 자극, 선도지구 이슈가 모멘텀."},
  {"title":"경기 안양시 동안구 평촌래미안푸르지오 84㎡ 9억","source":"이투데이","url":"https://www.etoday.co.kr/news/view/2509171","date":"2025-09-22","summary":"안양 동안구 평촌래미안푸르지오 9억(+0.5억, 5%) 상승 거래.","category":"price","comment":"평촌 학군·교통 수요 견조, 1기 신도시 정비 기대가 안양 가격 지지."},
  {"title":"경기 부천시 원미구 중동 센트럴파크푸르지오 84.82㎡ 11.3억","source":"국토부 실거래가","url":"https://zippoom.com/bucheon","date":"2026-01-19","summary":"부천 원미구 중동 센트럴파크푸르지오 전용 84.82㎡ 11.3억, 84.9㎡ 13.98억(2025.12).","category":"price","comment":"1기 신도시 중동 신축 국평 11~14억대, 노후계획도시 선도지구 기대가 지지."},
  {"title":"경기 부천시 원미구 중동 힐스테이트중동 84.94㎡ 12.55억","source":"국토부 실거래가","url":"https://zippoom.com/bucheon","date":"2026-02-23","summary":"부천 원미구 중동 힐스테이트중동 전용 84.94㎡ 12.55억 매매.","category":"price","comment":"중동 신축 국평 12억대, 7호선·GTX-B(부천종합운동장) 호재가 핵심지 지지."},
  {"title":"경기 부천시 원미구 상동 행복한마을 112.15㎡ 10.8억","source":"국토부 실거래가","url":"https://zippoom.com/bucheon","date":"2026-02-04","summary":"부천 원미구 상동 행복한마을 전용 112.15㎡ 10.8억 매매.","category":"price","comment":"상동 대형 구축 11억 선, 1기 신도시 정비 기대가 노후 대지지분 부각."},
  {"title":"경기 고양시 일산동구 킨텍스원시티M2블럭 104.9㎡ 16.4억","source":"국토부 실거래가","url":"https://zippoom.com/goyang","date":"2026-04-05","summary":"고양 일산동구 장항동 킨텍스원시티M2 전용 104.9㎡ 16.4억, 84.5㎡ 11.8억(2025.9).","category":"price","comment":"GTX-A 킨텍스역 신축 대단지가 일산 최상단, 광역급행 호재가 일산서부 견인."},
  {"title":"경기 고양시 일산동구 킨텍스원시티M3블럭 84.5㎡ 12.1억","source":"국토부 실거래가","url":"https://zippoom.com/goyang","date":"2026-04-18","summary":"고양 일산동구 장항동 킨텍스원시티M3 전용 84.5㎡ 12.1억, 84.44㎡ 12.9억(2025.12).","category":"price","comment":"킨텍스 신축 국평 12억대, GTX-A 개통 기대가 일산 신축 프리미엄."},
  {"title":"경기 고양시 덕양구 덕은동 DMC자이더리버 84.99㎡ 12.75억","source":"국토부 실거래가","url":"https://zippoom.com/goyang","date":"2026-04-24","summary":"고양 덕양구 덕은동 DMC자이더리버 전용 84.99㎡ 12.75억 매매.","category":"price","comment":"덕은지구 한강변 신축 국평 12억대, 상암DMC 접근성이 덕양 서남부 견인."},
  {"title":"경기 고양시 일산동구 백석동 일산요진와이시티 84.49㎡ 8.9억","source":"국토부 실거래가","url":"https://zippoom.com/goyang","date":"2026-05-04","summary":"고양 일산동구 백석동 일산요진와이시티 전용 84.49㎡ 8.9억(2025.9 9.2억 대비 조정).","category":"price","comment":"백석 대단지 국평 9억 안팎, GTX-A 수혜 기대와 가격 부담 혼재로 보합."},
  {"title":"경기 고양시 일산동구 킨텍스원시티M3블럭 84.5㎡ 전세 4.6억","source":"국토부 실거래가","url":"https://zippoom.com/goyang-kintex","date":"2025-12-27","summary":"고양 일산동구 킨텍스원시티M3 전용 84.5㎡ 전세 4.6억 신고(임대차).","category":"price","comment":"매매 12억 대비 전세 4억대로 전세가율 낮아 갭 부담 큰 신축 특성."},
  {"title":"인천 미추홀구 학익동 시티오씨엘1단지 85㎡ 6.75억·용현동 인천SKSkyVIEW 84.99㎡ 5.65억","source":"국토부 실거래가","url":"https://zippoom.com/michuhol","date":"2025-12-31","summary":"미추홀구 학익동 시티오씨엘1단지 전용 85㎡ 6.75억(12/31), 용현동 인천SKSkyVIEW 84.99㎡ 5.65억(1/27). 미추홀 평당 1533만(+5.3%).","category":"price","comment":"학익·용현 신축 대단지가 관망 속 거래 유지, 비규제 인천에서 신축 위주 선별."},
  {"title":"인천 미추홀구 주안동 힐스테이트푸르지오주안 59.96㎡ 4.85억·학익동 힐스테이트학익 85㎡ 6.28억","source":"국토부 실거래가","url":"https://zippoom.com/michuhol","date":"2026-02-04","summary":"미추홀구 주안동 힐스테이트푸르지오주안 전용 59.96㎡ 4.85억(2/4), 학익동 힐스테이트학익 85㎡ 6.28억(1/27).","category":"price","comment":"주안·학익 역세권 신축 5~6억대, 분상제 미적용 구도심 신축이 인천 실수요 핵심."},
  {"title":"인천 아파트 신고가 비중 미추홀 6.3% 최고·계양 1.1% 최저(5월)","source":"인천in","url":"https://www.incheonin.com/news/articleView.html?idxno=118519","date":"2026-06-09","summary":"직방 집계 5월 인천 신고가 비중 2.8%, 미추홀 6.3%·부평 4.0%·동구 3.1%·서구 2.9%·계양 1.1%.","category":"macro","comment":"수도권 신고가 비중 첫 10% 하회, 인천도 관망세 속 역세권·신축·대단지에 신고가 집중."}
]
